{
  "type": "dto",
  "module": "processdefinition",
  "name": "ProcessArtifactRequestDTO",
  "template": "classic",
  "enableCustonValidation": false,
  "attributes": [
    {
      "name": "name",
      "objectType": "java",
      "type": "string",
      "required": true,
      "before": false,
      "after": false,
      "positive": false,
      "isEmail": false,
      "isUrl": false,
      "primaryKey": false
    },
    {
      "name": "formKey",
      "objectType": "java",
      "type": "string",
      "required": true,
      "before": false,
      "after": false,
      "positive": false,
      "isEmail": false,
      "isUrl": false,
      "primaryKey": false
    },
    {
      "name": "candidateGroups",
      "objectType": "java",
      "type": "string",
      "required": false,
      "before": false,
      "after": false,
      "positive": false,
      "isEmail": false,
      "isUrl": false,
      "primaryKey": false,
      "collectionType": "none"
    },
    {
      "name": "dueDate",
      "objectType": "java",
      "type": "string",
      "required": false,
      "before": false,
      "after": false,
      "positive": false,
      "isEmail": false,
      "isUrl": false,
      "primaryKey": false
    },
    {
      "name": "priority",
      "objectType": "java",
      "type": "integer",
      "required": false,
      "before": false,
      "after": false,
      "positive": false,
      "isEmail": false,
      "isUrl": false,
      "primaryKey": false
    }
  ],
  "id": "6plsof8l2z"
}